Metadata-Version: 1.1
Name: staticlocal
Version: 0.0.1
Summary: An implementation of static local variables, as familiar from C
Home-page: https://github.com/billsix/staticlocal
Author: William Emerison Six
Author-email: billsix@gmail.com
License: MIT
Keywords: staticlocal
Platform: UNKNOWN
Classifier: Development Status :: 3 - Alpha
Classifier: Topic :: Utilities
Classifier: License :: OSI Approved :: MIT License
